[
  {
    "kind": "Start",
    "sim_time_sec": 0.0,
    "source": "Orchestrator"
  },
  {
    "kind": "MaxThrust",
    "sim_time_sec": 0.01,
    "source": "Analysis",
    "state": {
      "time_sec": 0.01,
      "position": {
        "lat_deg": 35.00000000044573,
        "lon_deg": 139.0,
        "alt_agl_m": 0.0028426424991766343
      },
      "velocity": {
        "true_airspeed_mps": 0.5686151026696125,
        "ground_speed_mps": 0.009923701878167818,
        "u_mps": 0.5686151026696125,
        "v_mps": 0.0,
        "w_mps": 0.0
      },
      "attitude": {
        "pitch_deg": 89.0,
        "roll_deg": 0.0,
        "yaw_deg": 0.0
      },
      "angular_rates": {
        "p_rad_sec": 0.0,
        "q_rad_sec": 0.0,
        "r_rad_sec": 0.0
      },
      "acceleration": {
        "ax_mps2": 56.86151026696125,
        "ay_mps2": 0.0,
        "az_mps2": 0.0
      },
      "aero": {
        "alpha_deg": 0.0,
        "beta_deg": 0.0,
        "qbar_pa": 0.0
      },
      "thrust_n": 2000.0,
      "mach": 0.0
    }
  },
  {
    "kind": "LaunchClear",
    "sim_time_sec": 0.4200000000000002,
    "source": "LaunchRail",
    "state": {
      "time_sec": 0.4200000000000002,
      "position": {
        "lat_deg": 35.000000800718965,
        "lon_deg": 139.0,
        "alt_agl_m": 5.106576670398575
      },
      "velocity": {
        "true_airspeed_mps": 24.553513078259694,
        "ground_speed_mps": 0.42851788970494653,
        "u_mps": 24.553513078259694,
        "v_mps": 0.0,
        "w_mps": 0.0
      },
      "attitude": {
        "pitch_deg": 89.0,
        "roll_deg": 0.0,
        "yaw_deg": 0.0
      },
      "angular_rates": {
        "p_rad_sec": 0.0,
        "q_rad_sec": 0.0,
        "r_rad_sec": 0.0
      },
      "acceleration": {
        "ax_mps2": 60.110245963435176,
        "ay_mps2": 0.0,
        "az_mps2": 0.0
      },
      "aero": {
        "alpha_deg": 0.0,
        "beta_deg": 0.0,
        "qbar_pa": 0.0
      },
      "thrust_n": 2000.0,
      "mach": 0.0
    }
  },
  {
    "kind": "EngineBurnout",
    "sim_time_sec": 1.0000000000000007,
    "source": "JsbSim",
    "state": {
      "time_sec": 1.0000000000000007,
      "position": {
        "lat_deg": 35.000005663428524,
        "lon_deg": 138.999994008468,
        "alt_agl_m": 29.94827677314476
      },
      "velocity": {
        "true_airspeed_mps": 60.86835212894468,
        "ground_speed_mps": 4.841360990908504,
        "u_mps": 55.58559606983112,
        "v_mps": 25.187108693159832,
        "w_mps": 0.09364868232322351
      },
      "attitude": {
        "pitch_deg": 61.19027802482889,
        "roll_deg": -87.91505578994543,
        "yaw_deg": 271.82761452606917
      },
      "angular_rates": {
        "p_rad_sec": 0.0001382862344627058,
        "q_rad_sec": -0.00048444675817385435,
        "r_rad_sec": -3.6475495867513477
      },
      "acceleration": {
        "ax_mps2": -26.453256906735312,
        "ay_mps2": 199.02014211277486,
        "az_mps2": 0.13452445177580705
      },
      "aero": {
        "alpha_deg": 0.09913646727515493,
        "beta_deg": 27.193004804270476,
        "qbar_pa": 2262.7848471759944
      },
      "thrust_n": 1999.9999999999704,
      "mach": 0.17893061732124604
    }
  },
  {
    "kind": "Apogee",
    "sim_time_sec": 7.519999999999884,
    "source": "JsbSim",
    "state": {
      "time_sec": 7.519999999999884,
      "position": {
        "lat_deg": 35.000077347850436,
        "lon_deg": 138.99958480110365,
        "alt_agl_m": 231.0425500049629
      },
      "velocity": {
        "true_airspeed_mps": 2.834500510963303,
        "ground_speed_mps": 5.401438229769497,
        "u_mps": 4.6285753728271475,
        "v_mps": -1.105381247773447,
        "w_mps": 2.921815570191572
      },
      "attitude": {
        "pitch_deg": 6.708980822496298,
        "roll_deg": -71.60468832028711,
        "yaw_deg": 250.60753903873896
      },
      "angular_rates": {
        "p_rad_sec": -1.5217316288335931,
        "q_rad_sec": 4.851648008760686,
        "r_rad_sec": -8.28033843384329
      },
      "acceleration": {
        "ax_mps2": -6.165710128040643,
        "ay_mps2": 24.645204420655688,
        "az_mps2": 23.839747502719025
      },
      "aero": {
        "alpha_deg": 45.840238191335494,
        "beta_deg": -22.966963128539,
        "qbar_pa": 4.812873342498897
      },
      "thrust_n": 0.0,
      "mach": 0.008351366791409078
    }
  },
  {
    "kind": "ParachuteOpen",
    "sim_time_sec": 8.529999999999863,
    "source": "Orchestrator",
    "state": {
      "time_sec": 8.529999999999863,
      "position": {
        "lat_deg": 35.00008343773601,
        "lon_deg": 138.99952540351737,
        "alt_agl_m": 224.617738549798
      },
      "velocity": {
        "true_airspeed_mps": 11.565039592963963,
        "ground_speed_mps": 5.401895719601088,
        "u_mps": 7.870492596379329,
        "v_mps": 7.899061429483066,
        "w_mps": 5.705581077468407
      },
      "attitude": {
        "pitch_deg": -62.2922070351225,
        "roll_deg": 37.17316801715037,
        "yaw_deg": 129.17434574708543
      },
      "angular_rates": {
        "p_rad_sec": -5.567506232608253,
        "q_rad_sec": -4.417870236626553,
        "r_rad_sec": -8.229271267179366
      },
      "acceleration": {
        "ax_mps2": -31.13387974183472,
        "ay_mps2": 35.78580244286883,
        "az_mps2": 12.765792760865523
      },
      "aero": {
        "alpha_deg": 30.19943755291165,
        "beta_deg": 26.415158649462136,
        "qbar_pa": 80.17054594113934
      },
      "thrust_n": 0.0,
      "mach": 0.03407191245639225
    }
  },
  {
    "kind": "MaxAxialAcceleration",
    "sim_time_sec": 13.35999999999976,
    "source": "Analysis",
    "state": {
      "time_sec": 13.35999999999976,
      "position": {
        "lat_deg": 35.00012088269768,
        "lon_deg": 138.9992437189713,
        "alt_agl_m": 57.53940309470451
      },
      "velocity": {
        "true_airspeed_mps": 57.4717767714644,
        "ground_speed_mps": 5.353020390565742,
        "u_mps": -16.59820232892715,
        "v_mps": -48.608139401349504,
        "w_mps": -26.19776705090366
      },
      "attitude": {
        "pitch_deg": 11.44309829035377,
        "roll_deg": -117.65316544055993,
        "yaw_deg": 100.94078459897125
      },
      "angular_rates": {
        "p_rad_sec": 10.118216023303567,
        "q_rad_sec": 25.863764487205064,
        "r_rad_sec": -8.290659043027295
      },
      "acceleration": {
        "ax_mps2": 1084.6673765968596,
        "ay_mps2": -412.16720277188745,
        "az_mps2": 57.91399234474858
      },
      "aero": {
        "alpha_deg": -116.94547727807534,
        "beta_deg": -58.23151540857476,
        "qbar_pa": 2011.9534090918617
      },
      "thrust_n": 0.0,
      "mach": 0.16899856726917473
    }
  },
  {
    "kind": "MaxLateralAcceleration",
    "sim_time_sec": 14.179999999999742,
    "source": "Analysis",
    "state": {
      "time_sec": 14.179999999999742,
      "position": {
        "lat_deg": 35.000128411120826,
        "lon_deg": 138.9991962302648,
        "alt_agl_m": 7.385576989838659
      },
      "velocity": {
        "true_airspeed_mps": 64.93862991433247,
        "ground_speed_mps": 5.540258580660354,
        "u_mps": 52.80683243522179,
        "v_mps": 37.3276491898025,
        "w_mps": -7.6664853513202225
      },
      "attitude": {
        "pitch_deg": -53.701790306308084,
        "roll_deg": 109.86216416501036,
        "yaw_deg": 1.6875668106310397
      },
      "angular_rates": {
        "p_rad_sec": -12.699608385819124,
        "q_rad_sec": -27.072262711029815,
        "r_rad_sec": -7.230011336908509
      },
      "acceleration": {
        "ax_mps2": -471.07107679053195,
        "ay_mps2": 485.9096268667371,
        "az_mps2": -956.5438535813753
      },
      "aero": {
        "alpha_deg": -11.196054443779767,
        "beta_deg": 33.92407442607546,
        "qbar_pa": 2581.116060183277
      },
      "thrust_n": 0.0,
      "mach": 0.19084714663261673
    }
  },
  {
    "kind": "MaxDynamicPressureAlpha",
    "sim_time_sec": 14.27999999999974,
    "source": "Analysis",
    "state": {
      "time_sec": 14.27999999999974,
      "position": {
        "lat_deg": 35.00012910208266,
        "lon_deg": 138.99919000882792,
        "alt_agl_m": 0.8524096585441179
      },
      "velocity": {
        "true_airspeed_mps": 65.84803504866626,
        "ground_speed_mps": 6.16634607647428,
        "u_mps": -50.33463181602578,
        "v_mps": 42.56306617946697,
        "w_mps": 4.266292736784351
      },
      "attitude": {
        "pitch_deg": 50.353499866220886,
        "roll_deg": 76.01314727236372,
        "yaw_deg": 194.5390536879648
      },
      "angular_rates": {
        "p_rad_sec": 12.89540863186952,
        "q_rad_sec": -28.286837878292378,
        "r_rad_sec": -10.767495306586861
      },
      "acceleration": {
        "ax_mps2": -341.5608393067543,
        "ay_mps2": -479.58976911973696,
        "az_mps2": 886.6692005093934
      },
      "aero": {
        "alpha_deg": 172.21864656372455,
        "beta_deg": 38.84227518916427,
        "qbar_pa": 2655.5797455474626
      },
      "thrust_n": 0.0,
      "mach": 0.1935055228079192
    }
  },
  {
    "kind": "Landed",
    "sim_time_sec": 14.29999999999974,
    "source": "JsbSim",
    "state": {
      "time_sec": 14.29999999999974,
      "position": {
        "lat_deg": 35.000129235837434,
        "lon_deg": 138.9991887103204,
        "alt_agl_m": -0.4648943262432408
      },
      "velocity": {
        "true_airspeed_mps": 66.02537728564721,
        "ground_speed_mps": 5.878895757734436,
        "u_mps": -51.448808727641,
        "v_mps": 35.44936568256429,
        "w_mps": 21.944696743164933
      },
      "attitude": {
        "pitch_deg": 47.43515193335948,
        "roll_deg": 52.63712101963336,
        "yaw_deg": 142.64196494038075
      },
      "angular_rates": {
        "p_rad_sec": 18.84880352314239,
        "q_rad_sec": -25.104937824377544,
        "r_rad_sec": -11.449951820271252
      },
      "acceleration": {
        "ax_mps2": 143.63338241386688,
        "ay_mps2": -168.9766261302136,
        "az_mps2": 635.2260851618862
      },
      "aero": {
        "alpha_deg": 153.8518624831858,
        "beta_deg": 32.081657137386564,
        "qbar_pa": 2670.2407218681547
      },
      "thrust_n": 0.0,
      "mach": 0.19402378999941466
    }
  },
  {
    "kind": "MaxQ",
    "sim_time_sec": 14.29999999999974,
    "source": "Analysis",
    "state": {
      "time_sec": 14.29999999999974,
      "position": {
        "lat_deg": 35.000129235837434,
        "lon_deg": 138.9991887103204,
        "alt_agl_m": -0.4648943262432408
      },
      "velocity": {
        "true_airspeed_mps": 66.02537728564721,
        "ground_speed_mps": 5.878895757734436,
        "u_mps": -51.448808727641,
        "v_mps": 35.44936568256429,
        "w_mps": 21.944696743164933
      },
      "attitude": {
        "pitch_deg": 47.43515193335948,
        "roll_deg": 52.63712101963336,
        "yaw_deg": 142.64196494038075
      },
      "angular_rates": {
        "p_rad_sec": 18.84880352314239,
        "q_rad_sec": -25.104937824377544,
        "r_rad_sec": -11.449951820271252
      },
      "acceleration": {
        "ax_mps2": 143.63338241386688,
        "ay_mps2": -168.9766261302136,
        "az_mps2": 635.2260851618862
      },
      "aero": {
        "alpha_deg": 153.8518624831858,
        "beta_deg": 32.081657137386564,
        "qbar_pa": 2670.2407218681547
      },
      "thrust_n": 0.0,
      "mach": 0.19402378999941466
    }
  },
  {
    "kind": "MaxAirspeed",
    "sim_time_sec": 14.29999999999974,
    "source": "Analysis",
    "state": {
      "time_sec": 14.29999999999974,
      "position": {
        "lat_deg": 35.000129235837434,
        "lon_deg": 138.9991887103204,
        "alt_agl_m": -0.4648943262432408
      },
      "velocity": {
        "true_airspeed_mps": 66.02537728564721,
        "ground_speed_mps": 5.878895757734436,
        "u_mps": -51.448808727641,
        "v_mps": 35.44936568256429,
        "w_mps": 21.944696743164933
      },
      "attitude": {
        "pitch_deg": 47.43515193335948,
        "roll_deg": 52.63712101963336,
        "yaw_deg": 142.64196494038075
      },
      "angular_rates": {
        "p_rad_sec": 18.84880352314239,
        "q_rad_sec": -25.104937824377544,
        "r_rad_sec": -11.449951820271252
      },
      "acceleration": {
        "ax_mps2": 143.63338241386688,
        "ay_mps2": -168.9766261302136,
        "az_mps2": 635.2260851618862
      },
      "aero": {
        "alpha_deg": 153.8518624831858,
        "beta_deg": 32.081657137386564,
        "qbar_pa": 2670.2407218681547
      },
      "thrust_n": 0.0,
      "mach": 0.19402378999941466
    }
  },
  {
    "kind": "MaxAngularRate",
    "sim_time_sec": 14.29999999999974,
    "source": "Analysis",
    "state": {
      "time_sec": 14.29999999999974,
      "position": {
        "lat_deg": 35.000129235837434,
        "lon_deg": 138.9991887103204,
        "alt_agl_m": -0.4648943262432408
      },
      "velocity": {
        "true_airspeed_mps": 66.02537728564721,
        "ground_speed_mps": 5.878895757734436,
        "u_mps": -51.448808727641,
        "v_mps": 35.44936568256429,
        "w_mps": 21.944696743164933
      },
      "attitude": {
        "pitch_deg": 47.43515193335948,
        "roll_deg": 52.63712101963336,
        "yaw_deg": 142.64196494038075
      },
      "angular_rates": {
        "p_rad_sec": 18.84880352314239,
        "q_rad_sec": -25.104937824377544,
        "r_rad_sec": -11.449951820271252
      },
      "acceleration": {
        "ax_mps2": 143.63338241386688,
        "ay_mps2": -168.9766261302136,
        "az_mps2": 635.2260851618862
      },
      "aero": {
        "alpha_deg": 153.8518624831858,
        "beta_deg": 32.081657137386564,
        "qbar_pa": 2670.2407218681547
      },
      "thrust_n": 0.0,
      "mach": 0.19402378999941466
    }
  },
  {
    "kind": "ParachuteLanded",
    "sim_time_sec": 20.309999999999814,
    "source": "Parachute",
    "state": {
      "time_sec": 20.309999999999814,
      "position": {
        "lat_deg": 35.00009633731042,
        "lon_deg": 138.99972312652397,
        "alt_agl_m": 0.0
      },
      "velocity": {
        "true_airspeed_mps": 3.0,
        "ground_speed_mps": 0.0,
        "u_mps": 0.0,
        "v_mps": 0.0,
        "w_mps": 0.0
      },
      "attitude": {
        "pitch_deg": 0.0,
        "roll_deg": 0.0,
        "yaw_deg": 0.0
      },
      "angular_rates": {
        "p_rad_sec": 0.0,
        "q_rad_sec": 0.0,
        "r_rad_sec": 0.0
      },
      "acceleration": {
        "ax_mps2": 0.0,
        "ay_mps2": 0.0,
        "az_mps2": 0.0
      },
      "aero": {
        "alpha_deg": 0.0,
        "beta_deg": 0.0,
        "qbar_pa": 0.0
      },
      "thrust_n": 0.0,
      "mach": 0.0
    }
  }
]